dataflake/docbuilder/__init__.py
dataflake/docbuilder/builder.py
dataflake/docbuilder/rcs.py
dataflake/docbuilder/utils.py
dataflake/docbuilder/index_template/conf.py
dataflake/docbuilder/index_template/index.rst.in
dataflake/docbuilder/index_template/_static/python.css
dataflake.docbuilder-2.5.dist-info/LICENSE.txt
dataflake.docbuilder-2.5.dist-info/METADATA
dataflake.docbuilder-2.5.dist-info/WHEEL
dataflake.docbuilder-2.5.dist-info/entry_points.txt
dataflake.docbuilder-2.5.dist-info/top_level.txt
dataflake.docbuilder-2.5.dist-info/RECORD
