Metadata-Version: 2.1
Name: dataflake.docbuilder
Version: 2.5
Summary: Automated Sphinx documentation builder
Home-page: https://github.com/dataflake/dataflake.docbuilder
Author: Jens Vagelpohl and contributors
Author-email: jens@dataflake.org
License: ZPL 2.1
Project-URL: Documentation, https://dataflakedocbuilder.readthedocs.io/
Project-URL: Sources, https://github.com/dataflake/dataflake.docbuilder
Project-URL: Issue Tracker, https://github.com/dataflake/dataflake.docbuilder/issues
Keywords: sphinx documentation
Classifier: Development Status :: 5 - Production/Stable
Classifier: Intended Audience :: Developers
Classifier: License :: OSI Approved :: Zope Public License
Classifier: Operating System :: OS Independent
Classifier: Programming Language :: Python :: 3
Classifier: Programming Language :: Python :: 3.7
Classifier: Programming Language :: Python :: 3.8
Classifier: Programming Language :: Python :: 3.9
Classifier: Programming Language :: Python :: 3.10
Classifier: Programming Language :: Python :: 3.11
Classifier: Programming Language :: Python :: 3.12
Classifier: Programming Language :: Python :: Implementation :: CPython
Classifier: Programming Language :: Python :: Implementation :: PyPy
Classifier: Topic :: Software Development :: Libraries :: Python Modules
Requires-Python: >=3.7
License-File: LICENSE.txt
Requires-Dist: setuptools
Requires-Dist: sphinx
Requires-Dist: zc.buildout
Requires-Dist: zc.recipe.egg
Provides-Extra: docs
Requires-Dist: pkginfo ; extra == 'docs'
Requires-Dist: sphinx-rtd-theme ; extra == 'docs'
